lambda_app_common/Database.py
lambda_app_common/Environment.py
lambda_app_common/Events.py
lambda_app_common/Factory.py
lambda_app_common/Models.py
lambda_app_common/Repository.py
lambda_app_common/RequestContext.py
lambda_app_common/Service.py
lambda_app_common/TaskProcessor.py
lambda_app_common/__init__ .py
lambda_app_common/imports.py
lambda_app_common-1.2.1.dist-info/METADATA
lambda_app_common-1.2.1.dist-info/WHEEL
lambda_app_common-1.2.1.dist-info/licenses/LICENSE
lambda_app_common-1.2.1.dist-info/RECORD
